Metadata-Version: 2.1
Name: zorb
Version: 0.1.5
Summary: Python SDK for the Zorb Engine
Home-page: https://github.com/SomaticLabs/ZorbPy
Author: Somatic Labs
Author-email: developers@somaticlabs.io
License: UNKNOWN
Platform: UNKNOWN
Classifier: Programming Language :: Python :: 2.7
Classifier: License :: OSI Approved :: MIT License
Classifier: Operating System :: MacOS
Classifier: Operating System :: POSIX :: Linux
Classifier: Topic :: Scientific/Engineering :: Human Machine Interfaces
